xmlrfc2md/__init__.py
xmlrfc2md/xmlrfc2md.py
xmlrfc2md-0.1.0.dist-info/LICENSE
xmlrfc2md-0.1.0.dist-info/METADATA
xmlrfc2md-0.1.0.dist-info/WHEEL
xmlrfc2md-0.1.0.dist-info/entry_points.txt
xmlrfc2md-0.1.0.dist-info/top_level.txt
xmlrfc2md-0.1.0.dist-info/RECORD
